smashcima/__init__.py
smashcima/_version.py
smashcima/config.py
smashcima/random_between.py
smashcima/assets/AssetBundle.py
smashcima/assets/AssetRepository.py
smashcima/assets/__init__.py
smashcima/assets/download_file.py
smashcima/assets/datasets/MuscimaPP.py
smashcima/assets/datasets/OmniOMRProto.py
smashcima/assets/glyphs/__init__.py
smashcima/assets/glyphs/mung/MungGlyphMetadata.py
smashcima/assets/glyphs/mung/README.md
smashcima/assets/glyphs/mung/extraction/BaseSymbolExtractor.py
smashcima/assets/glyphs/mung/extraction/ExtractedBag.py
smashcima/assets/glyphs/mung/extraction/MungDocument.py
smashcima/assets/glyphs/mung/extraction/MungSymbolExtractor.py
smashcima/assets/glyphs/mung/extraction/PointCloud.py
smashcima/assets/glyphs/mung/extraction/accidentals.py
smashcima/assets/glyphs/mung/extraction/get_line_endpoints.py
smashcima/assets/glyphs/mung/extraction/mung_mask_to_smashcima_sprite_bitmap.py
smashcima/assets/glyphs/mung/repository/GlyphsIndex.py
smashcima/assets/glyphs/mung/repository/LineGlyphsIndex.py
smashcima/assets/glyphs/mung/repository/MungSymbolRepository.py
smashcima/assets/glyphs/mung/repository/PackedGlyph.py
smashcima/assets/glyphs/mung/repository/PackedLineGlyph.py
smashcima/assets/glyphs/mung/repository/PackedLineList.py
smashcima/assets/glyphs/mung/utils/get_new_node_id.py
smashcima/assets/glyphs/mung/utils/link_nodes_to_staves.py
smashcima/assets/glyphs/mung/utils/link_stafflines_to_staves.py
smashcima/assets/glyphs/muscima_pp/MppGlyphMetadata.py
smashcima/assets/glyphs/muscima_pp/MppPage.py
smashcima/assets/glyphs/muscima_pp/MuscimaPPGlyphs.py
smashcima/assets/glyphs/muscima_pp/PointCloud.py
smashcima/assets/glyphs/muscima_pp/__init__.py
smashcima/assets/glyphs/muscima_pp/__main__.py
smashcima/assets/glyphs/muscima_pp/get_symbols.py
smashcima/assets/glyphs/omni_omr/OmniOMRGlyphMetadata.py
smashcima/assets/glyphs/omni_omr/OmniOMRGlyphs.py
smashcima/assets/glyphs/omni_omr/OmniOMRSymbolExtractor.py
smashcima-1.1.2.dist-info/METADATA
smashcima-1.1.2.dist-info/WHEEL
smashcima-1.1.2.dist-info/licenses/LICENSE
smashcima-1.1.2.dist-info/RECORD
