Metadata-Version: 2.4
Name: smashcima
Version: 1.1.2
Summary: Training data synthesizer for OMR
Project-URL: Homepage, https://github.com/OMR-Research/Smashcima
Project-URL: Source, https://github.com/OMR-Research/Smashcima
Project-URL: Issues, https://github.com/OMR-Research/Smashcima/issues
Author-email: Jiří Mayer <mayer@ufal.mff.cuni.cz>
License-File: LICENSE
Classifier: License :: OSI Approved :: Apache Software License
Classifier: Operating System :: OS Independent
Classifier: Programming Language :: Python :: 3
Requires-Python: >=3.8
Requires-Dist: albumentations
Requires-Dist: augraphy
Requires-Dist: mung
Requires-Dist: muscima
Requires-Dist: nameof
Requires-Dist: numpy
Requires-Dist: opencv-contrib-python
Requires-Dist: punq
Requires-Dist: requests
Requires-Dist: scikit-image
Requires-Dist: tqdm
Provides-Extra: gradio
Requires-Dist: coolname; extra == 'gradio'
Requires-Dist: gradio; extra == 'gradio'
Provides-Extra: jupyter
Requires-Dist: ipycytoscape; extra == 'jupyter'
Requires-Dist: ipympl; extra == 'jupyter'
Requires-Dist: jupyter; extra == 'jupyter'
Requires-Dist: voila; extra == 'jupyter'
